{
  "users": [
    {
      "name": "Sierra Melendez",
      "email": "nutyranut@mailinator.net",
      "password": "12345678",
      "usersId": "haQsfFFg7"
    },
    {
      "name": "Liberty Mayer",
      "email": "gitoc@mailinator.net",
      "password": "12345678",
      "usersId": "45W1RkFd6"
    },
    {
      "name": "Britanney Arnold",
      "email": "qybu@mailinator.com",
      "password": "12345678",
      "usersId": "o29Qhfp-P"
    },
    {
      "name": "Macaulay Marshall",
      "email": "gicazovy@mailinator.com",
      "password": "12345678",
      "usersId": "ToZTpT5uW"
    },
    {
      "name": "Tatiana Hoffman",
      "email": "ketoky@mailinator.net",
      "password": "12345678",
      "usersId": "0L14nmRxy"
    },
    {
      "name": "Blossom Griffith",
      "email": "kacexo@mailinator.com",
      "password": "Pa$$w0rd!",
      "usersId": "v1hgyE1Pn"
    },
    {
      "name": "Cade Rhodes",
      "email": "povowusynu@mailinator.com",
      "password": "Pa$$w0rd!",
      "usersId": "xidmzDuDv"
    },
    {
      "name": "Geoffrey Walton",
      "email": "xywuwew@mailinator.com",
      "password": "Pa$$w0rd!",
      "usersId": "AAKuzIMyj"
    },
    {
      "name": "Burton Patrick",
      "email": "xapa@mailinator.com",
      "password": "Pa$$w0rd!",
      "usersId": "1APZ_DCrN"
    },
    {
      "name": "Ferdinand Solis",
      "email": "padof@mailinator.com",
      "password": "Pa$$w0rd!",
      "usersId": "HjeC-O_YP"
    },
    {
      "name": "Ferdinand Solis",
      "email": "padof@mailinator.com",
      "password": "Pa$$w0rd!",
      "usersId": "Lj1iuBftQ"
    }
  ],
  "count": 0
}